{
  "name": "Shengong CY7 Axe",
  "url": "https://icarus.fandom.com/wiki/Shengong_CY7_Axe",
  "description": "The Shengong CY7 Axe is a Workshop Axe geared towards combat, intrinsically dealing electric damage with the chance to significantly hinder targets. Ideally used with the Berserker talent, which increases axe melee damage.",
  "item_type": "craftable",
  "ingredients": {},
  "crafted_at": "Workshop",
  "tier": 0,
  "stats": {
    "damage": "+60 Felling Damage",
    "weight": "0.1 kg",
    "durability": "50,000"
  },
  "category": "axes",
  "harvested_from": [],
  "research_cost": null,
  "purchase_cost": null,
  "base_recipe": {
    "ingredients": {},
    "crafted_at": "Workshop"
  }
}