{
  "name": "Stone Axe",
  "url": "https://icarus.fandom.com/wiki/Stone_Axe",
  "description": "The Stone Axe is used primarily for chopping down trees and Small Trees , reducing them to usable Wood . In the process of chopping apart fallen trees, a small number of Sticks may be added to your inventory automatically.",
  "item_type": "weapon",
  "ingredients": {},
  "crafted_at": "Unknown",
  "tier": 1,
  "stats": {
    "damage": "+25 Felling Damage",
    "weight": "0.5 Kg",
    "durability": "20,000"
  },
  "category": "axes",
  "harvested_from": [],
  "research_cost": null,
  "purchase_cost": null,
  "base_recipe": {
    "ingredients": {},
    "crafted_at": "Unknown"
  }
}