{
  "name": "Titanium Pickaxe",
  "url": "https://icarus.fandom.com/wiki/Titanium_Pickaxe",
  "description": "The Titanium Pickaxe is the highest-tiered Pickaxe that can be crafted while on the surface of Icarus. When combined with a Tool Attachment Pack / Advanced Tool Attachment Pack , the Titanium Pickaxe surpasses the Inaris \"Neves\" Pickaxe in terms of mining.",
  "item_type": "craftable",
  "ingredients": {
    "Carbon Fiber": 4,
    "Steel Screw": 8,
    "Epoxy": 4,
    "Titanium Ingot": 12
  },
  "crafted_at": "Unknown",
  "tier": 4,
  "stats": {
    "damage": "49 - 55",
    "weight": "0.5 kg",
    "durability": "120,000"
  },
  "category": "pickaxes",
  "harvested_from": [],
  "research_cost": null,
  "purchase_cost": null,
  "base_recipe": {
    "ingredients": {
      "Carbon Fiber": 4,
      "Steel Screw": 8,
      "Epoxy": 4,
      "Titanium Ingot": 12
    },
    "crafted_at": "Unknown"
  }
}