{
  "name": "Anti-Parasitic Vaccine II",
  "url": "https://icarus.fandom.com/wiki/Anti-Parasitic_Vaccine_II",
  "description": "Anti-Parasitic Vaccine II is purchased in the Workshop on the Space Station . Vaccines are long lasting preventatives of aliments on Icarus, they provide a unqiue Status Effect , which makes surviving the enviroment without worry possible.",
  "item_type": "orbital",
  "ingredients": {},
  "crafted_at": "Workshop",
  "tier": 0,
  "stats": {},
  "category": "medicine",
  "harvested_from": [],
  "research_cost": 300,
  "purchase_cost": null,
  "base_recipe": {
    "ingredients": {},
    "crafted_at": "Workshop"
  }
}