{
  "name": "Battery Cavelight",
  "url": "https://icarus.fandom.com/wiki/Battery_Cavelight",
  "description": "The Battery Cavelight is a portable Light Source that can be deployed on a floor or wall to provide illumination in the surrounding area. It is good for marking a path through caves.",
  "item_type": "craftable",
  "ingredients": {},
  "crafted_at": "Fabricator",
  "tier": 4,
  "stats": {
    "weight": "2.0 Kg"
  },
  "category": "deployables",
  "harvested_from": [],
  "research_cost": null,
  "purchase_cost": null,
  "base_recipe": {
    "ingredients": {},
    "crafted_at": "Fabricator"
  }
}