{
  "name": "Watermelon",
  "url": "https://icarus.fandom.com/wiki/Watermelon",
  "description": "Watermelons are a common form ofPlantlifefound in theForestandRiverlandslocationson Icarus. When consumed by Prospectors, they replenishHungerandThirst.",
  "item_type": "ammunition",
  "ingredients": {},
  "crafted_at": "Unknown",
  "tier": 0,
  "stats": {},
  "category": "food",
  "harvested_from": [],
  "research_cost": null,
  "purchase_cost": null,
  "base_recipe": {
    "ingredients": {},
    "crafted_at": "Unknown"
  }
}