{
  "name": "Thatch Trapdoor",
  "url": "https://icarus.fandom.com/wiki/Thatch_Trapdoor",
  "description": "Thatch building pieces are very light-weight and are best suited as emergency shelters. While subject to damage from milder storms than any other material, they are light enough to carry and will still offer protection toDeployablesandStoragecontainers. Attaches to floors with trapdoor holes (hold R while holding a floor building piece and select the Trapdoor variant from the radial wheel).",
  "item_type": "craftable",
  "ingredients": {},
  "crafted_at": "Unknown",
  "tier": 0,
  "stats": {
    "weight": "1.0 kg",
    "durability": "250"
  },
  "category": "thatch building trim set",
  "harvested_from": [],
  "research_cost": null,
  "purchase_cost": null,
  "base_recipe": {
    "ingredients": {
      "Fiber": 10,
      "Stick": 4
    },
    "crafted_at": "Unknown"
  }
}