{
  "name": "Volatile Raw Exotics",
  "url": "https://icarus.fandom.com/wiki/Volatile_Raw_Exotics",
  "description": "While theExoticsprospectors found onOlympusandStyxwere originally believed to be the only known variation, the UDA has made a remarkable discovery. This unstable variant is different and appears to have an impact on the local flora not seen before.",
  "item_type": "unknown",
  "ingredients": {},
  "crafted_at": "Unknown",
  "tier": 0,
  "stats": {},
  "category": "minerals",
  "harvested_from": [],
  "research_cost": null,
  "purchase_cost": null
}