{
  "name": "Buffalo Vestige",
  "url": "https://icarus.fandom.com/wiki/Buffalo_Vestige",
  "description": "Buffalo Vestiges are used at theTrophy Benchto create aBuffalo Trophy, which can help prospectors complete theBestiary. They are also used at theAdvanced Textiles Bench/Electric Textiles Benchto makeBuffalo Rugs. Decorative purposes aside, both provide a boost to coziness, which increases the duration and effect of theWell Rested Buff.",
  "item_type": "ammunition",
  "ingredients": {},
  "crafted_at": "Unknown",
  "tier": 2,
  "stats": {},
  "category": "animal resources",
  "harvested_from": [],
  "research_cost": null,
  "purchase_cost": null,
  "base_recipe": {
    "ingredients": {},
    "crafted_at": "Unknown"
  }
}